README.md
poetry_project/__init__.py
poetry_project/util.py
pyproject.toml
poetry_project-0.3.0.dist-info/LICENSE
poetry_project-0.3.0.dist-info/WHEEL
poetry_project-0.3.0.dist-info/METADATA
poetry_project-0.3.0.dist-info/RECORD
