Metadata-Version: 2.1
Name: poetry-project
Version: 0.3.0
Summary: Read poetry project information such as name, version and description.
Author: Julian Stier
Author-email: mail@julian-stier.de
Requires-Python: >=3.5,<4.0
Classifier: Programming Language :: Python :: 3
Classifier: Programming Language :: Python :: 3.5
Classifier: Programming Language :: Python :: 3.6
Classifier: Programming Language :: Python :: 3.7
Classifier: Programming Language :: Python :: 3.8
Requires-Dist: importlib-metadata (>=1.5.0,<2.0.0)
Requires-Dist: importlib-resources (>=1.4.0,<2.0.0)
Requires-Dist: tomlkit (>=0.5.11,<0.6.0)
